Pytrium-0.1.2.dist-info/DESCRIPTION.rst
Pytrium-0.1.2.dist-info/METADATA
Pytrium-0.1.2.dist-info/RECORD
Pytrium-0.1.2.dist-info/WHEEL
Pytrium-0.1.2.dist-info/metadata.json
Pytrium-0.1.2.dist-info/top_level.txt
atrium/__init__.py
atrium/api.py
atrium/errors.py
atrium/requester.py
atrium/utils.py
atrium/models/__init__.py
atrium/models/user.py
